simple_snowflake_mcp/__init__.py
simple_snowflake_mcp/server.py
simple_snowflake_mcp_fastmcp-0.2.1.dist-info/METADATA
simple_snowflake_mcp_fastmcp-0.2.1.dist-info/WHEEL
simple_snowflake_mcp_fastmcp-0.2.1.dist-info/entry_points.txt
simple_snowflake_mcp_fastmcp-0.2.1.dist-info/licenses/LICENSE
simple_snowflake_mcp_fastmcp-0.2.1.dist-info/RECORD
