Metadata-Version: 2.4
Name: simple-snowflake-mcp-fastmcp
Version: 0.2.1
Summary: Simple Snowflake MCP Server to work behind a corporate proxy
Project-URL: Homepage, https://github.com/fastmcp-me/simple_snowflake_mcp#readme
Project-URL: Repository, https://github.com/fastmcp-me/simple_snowflake_mcp.git
Project-URL: Issues, https://github.com/fastmcp-me/simple_snowflake_mcp/issues
Author-email: Yann Barraud <yann@barraud.io>
License: MIT License
License-File: LICENSE
Keywords: mcp,proxy,server,snowflake
Classifier: License :: OSI Approved :: MIT License
Classifier: Operating System :: OS Independent
Classifier: Programming Language :: Python :: 3
Requires-Python: >=3.10
Requires-Dist: mcp>=1.10.1
Requires-Dist: pydantic
Requires-Dist: python-dotenv
Requires-Dist: pyyaml
Requires-Dist: snowflake-connector-python
